{
  "title": "Ventuno, la community Bitcoin italiana",
  "description": "Un punto di ritrovo per Bitcoiner tossici e massimalisti.",
  "keywords": "Bitcoin,Podcast,Lightning Network",
  "themeColor": "#f7931a",
  "cardImage": "/img/card/logo.png",
  "githubUrl": "https://github.com/ventunobtc",
  "twitterUrl": "https://twitter.com/VentunoBtc",
  "telegramUrl": "https://t.me/ventunobtc",
  "instagramUrl": "https://www.instagram.com/ventunobtc",
  "shopUrl": "http://ventuno.space/shop",
  "soundcloudUrl": "",
  "shoutoutUrl": "",
  "youtubeUrl": "https://youtube.com/@ventunobtc4191",
  "spotifyUrl": "https://open.spotify.com/show/3TG1XHlY0uX8HKrXdmTCMz",
  "appleUrl": "",
  "googleUrl": "",
  "podcastIndexUrl": "https://podcastindex.org/podcast/6677956",
  "overcastUrl": "",
  "anchorUrl": "https://anchor.fm/ventunobtc",
  "masterFeedUrl": "https://anchor.fm/s/ebe58594/podcast/rss",
  "publicFeedUrl": "https://ventuno.space/feed.xml",
  "nostr": "",
  "ticker": [
    "Non fidarti, Verifica!",
    "Gasparri è il miglior indicatore di prezzo dopo la coda di gatto",
    "Running bitcoin",
    "Puntare contro l'euro è senza senso. Fatelo se volete - Mario Draghi",
    "La lingua inglese è inadeguata #perfidaAlbione",
    "Le tasse sono un furto",
    "L'inflazione è una tassa nascosta",
    "Via libera al prelievo forzoso di Amato - 10 Luglio 1992",
    "Se non si scrive esattamente Bitcoin, è truffa",
    "Con l'euro lavoreremo un giorno di meno guadagnando come se lavorassimo un giorno di più - Romano Prodi, 1999"
  ]
}
